download_google_imgs/__init__.py
download_google_imgs/downloader.py
download_google_imgs-1.0.5.dist-info/METADATA
download_google_imgs-1.0.5.dist-info/WHEEL
download_google_imgs-1.0.5.dist-info/top_level.txt
download_google_imgs-1.0.5.dist-info/RECORD
