Metadata-Version: 2.1
Name: download_google_imgs
Version: 1.0.5
Summary: Python library to download images form Google Images with query.
Home-page: https://github.com/xtcpete/download_google_imgs
Author: Gonglin Chen
Author-email: xtcpetecgl@gmail.com
Keywords: google,images,scraping,image download,bulk image downloader
Classifier: Programming Language :: Python :: 3
Classifier: License :: OSI Approved :: MIT License
Classifier: Operating System :: OS Independent
Requires: selenium
Requires: tqdm
Requires: beautifulsoup4
